.hgignore
CHANGES.txt
LICENSE.txt
MANIFEST.in
README.txt
bootstrap.py
buildout.cfg
setup.py
js/__init__.py
js.knockback.egg-info/PKG-INFO
js.knockback.egg-info/SOURCES.txt
js.knockback.egg-info/dependency_links.txt
js.knockback.egg-info/entry_points.txt
js.knockback.egg-info/namespace_packages.txt
js.knockback.egg-info/not-zip-safe
js.knockback.egg-info/requires.txt
js.knockback.egg-info/top_level.txt
js/knockback/__init__.py
js/knockback/test_knockback.txt
js/knockback/resources/README.txt
js/knockback/resources/knockback.js
js/knockback/resources/knockback.min.js