Metadata-Version: 1.0
Name: js.knockback
Version: 0.16.7
Summary: Fanstatic packaging of Knockback.js
Home-page: UNKNOWN
Author: gocept Developers
Author-email: mail@gocept.com
License: BSD
Platform: UNKNOWN
